setup.py
yueyelib/__init__.py
yueyelib/hccmd.py
yueyelib/hclogo.py
yueyelib/hcprint.py
yueyelib.egg-info/PKG-INFO
yueyelib.egg-info/SOURCES.txt
yueyelib.egg-info/dependency_links.txt
yueyelib.egg-info/top_level.txt